[{"metricId": 6545556, "metricName": "DB|KPI|Time Spent in Executions (s)", "metricPath": "Databases|C2L_DMS|DB|KPI|Time Spent in Executions (s)", "frequency": "ONE_MIN", "metricValues": [{"startTimeInMillis": 1770013500000, "occurrences": 1, "current": 152, "min": 152, "max": 152, "useRange": false, "count": 1, "sum": 152, "value": 152, "standardDeviation": 0}, {"startTimeInMillis": 1770013560000, "occurrences": 1, "current": 181, "min": 181, "max": 181, "useRange": false, "count": 1, "sum": 181, "value": 181, "standardDeviation": 0}, {"startTimeInMillis": 1770013620000, "occurrences": 1, "current": 232, "min": 232, "max": 232, "useRange": false, "count": 1, "sum": 232, "value": 232, "standardDeviation": 0}, {"startTimeInMillis": 1770013680000, "occurrences": 1, "current": 238, "min": 238, "max": 238, "useRange": false, "count": 1, "sum": 238, "value": 238, "standardDeviation": 0}, {"startTimeInMillis": 1770013740000, "occurrences": 1, "current": 248, "min": 248, "max": 248, "useRange": false, "count": 1, "sum": 248, "value": 248, "standardDeviation": 0}, {"startTimeInMillis": 1770013800000, "occurrences": 1, "current": 239, "min": 239, "max": 239, "useRange": false, "count": 1, "sum": 239, "value": 239, "standardDeviation": 0}, {"startTimeInMillis": 1770013860000, "occurrences": 1, "current": 162, "min": 162, "max": 162, "useRange": false, "count": 1, "sum": 162, "value": 162, "standardDeviation": 0}, {"startTimeInMillis": 1770013920000, "occurrences": 1, "current": 189, "min": 189, "max": 189, "useRange": false, "count": 1, "sum": 189, "value": 189, "standardDeviation": 0}, {"startTimeInMillis": 1770013980000, "occurrences": 1, "current": 167, "min": 167, "max": 167, "useRange": false, "count": 1, "sum": 167, "value": 167, "standardDeviation": 0}, {"startTimeInMillis": 1770014040000, "occurrences": 1, "current": 179, "min": 179, "max": 179, "useRange": false, "count": 1, "sum": 179, "value": 179, "standardDeviation": 0}, {"startTimeInMillis": 1770014100000, "occurrences": 1, "current": 134, "min": 134, "max": 134, "useRange": false, "count": 1, "sum": 134, "value": 134, "standardDeviation": 0}, {"startTimeInMillis": 1770014160000, "occurrences": 1, "current": 210, "min": 210, "max": 210, "useRange": false, "count": 1, "sum": 210, "value": 210, "standardDeviation": 0}, {"startTimeInMillis": 1770014220000, "occurrences": 1, "current": 257, "min": 257, "max": 257, "useRange": false, "count": 1, "sum": 257, "value": 257, "standardDeviation": 0}, {"startTimeInMillis": 1770014280000, "occurrences": 1, "current": 266, "min": 266, "max": 266, "useRange": false, "count": 1, "sum": 266, "value": 266, "standardDeviation": 0}, {"startTimeInMillis": 1770014340000, "occurrences": 1, "current": 275, "min": 275, "max": 275, "useRange": false, "count": 1, "sum": 275, "value": 275, "standardDeviation": 0}, {"startTimeInMillis": 1770014400000, "occurrences": 1, "current": 240, "min": 240, "max": 240, "useRange": false, "count": 1, "sum": 240, "value": 240, "standardDeviation": 0}, {"startTimeInMillis": 1770014460000, "occurrences": 1, "current": 278, "min": 278, "max": 278, "useRange": false, "count": 1, "sum": 278, "value": 278, "standardDeviation": 0}, {"startTimeInMillis": 1770014520000, "occurrences": 1, "current": 328, "min": 328, "max": 328, "useRange": false, "count": 1, "sum": 328, "value": 328, "standardDeviation": 0}, {"startTimeInMillis": 1770014580000, "occurrences": 1, "current": 370, "min": 370, "max": 370, "useRange": false, "count": 1, "sum": 370, "value": 370, "standardDeviation": 0}, {"startTimeInMillis": 1770014640000, "occurrences": 1, "current": 416, "min": 416, "max": 416, "useRange": false, "count": 1, "sum": 416, "value": 416, "standardDeviation": 0}, {"startTimeInMillis": 1770014700000, "occurrences": 1, "current": 480, "min": 480, "max": 480, "useRange": false, "count": 1, "sum": 480, "value": 480, "standardDeviation": 0}, {"startTimeInMillis": 1770014760000, "occurrences": 1, "current": 434, "min": 434, "max": 434, "useRange": false, "count": 1, "sum": 434, "value": 434, "standardDeviation": 0}, {"startTimeInMillis": 1770014820000, "occurrences": 1, "current": 256, "min": 256, "max": 256, "useRange": false, "count": 1, "sum": 256, "value": 256, "standardDeviation": 0}, {"startTimeInMillis": 1770014880000, "occurrences": 1, "current": 251, "min": 251, "max": 251, "useRange": false, "count": 1, "sum": 251, "value": 251, "standardDeviation": 0}, {"startTimeInMillis": 1770014940000, "occurrences": 1, "current": 194, "min": 194, "max": 194, "useRange": false, "count": 1, "sum": 194, "value": 194, "standardDeviation": 0}, {"startTimeInMillis": 1770015000000, "occurrences": 1, "current": 182, "min": 182, "max": 182, "useRange": false, "count": 1, "sum": 182, "value": 182, "standardDeviation": 0}, {"startTimeInMillis": 1770015060000, "occurrences": 1, "current": 171, "min": 171, "max": 171, "useRange": false, "count": 1, "sum": 171, "value": 171, "standardDeviation": 0}, {"startTimeInMillis": 1770015120000, "occurrences": 1, "current": 129, "min": 129, "max": 129, "useRange": false, "count": 1, "sum": 129, "value": 129, "standardDeviation": 0}, {"startTimeInMillis": 1770015180000, "occurrences": 1, "current": 149, "min": 149, "max": 149, "useRange": false, "count": 1, "sum": 149, "value": 149, "standardDeviation": 0}, {"startTimeInMillis": 1770015240000, "occurrences": 1, "current": 116, "min": 116, "max": 116, "useRange": false, "count": 1, "sum": 116, "value": 116, "standardDeviation": 0}, {"startTimeInMillis": 1770015300000, "occurrences": 1, "current": 62, "min": 62, "max": 62, "useRange": false, "count": 1, "sum": 62, "value": 62, "standardDeviation": 0}, {"startTimeInMillis": 1770015360000, "occurrences": 1, "current": 60, "min": 60, "max": 60, "useRange": false, "count": 1, "sum": 60, "value": 60, "standardDeviation": 0}, {"startTimeInMillis": 1770015420000, "occurrences": 1, "current": 63, "min": 63, "max": 63, "useRange": false, "count": 1, "sum": 63, "value": 63, "standardDeviation": 0}, {"startTimeInMillis": 1770015480000, "occurrences": 1, "current": 63, "min": 63, "max": 63, "useRange": false, "count": 1, "sum": 63, "value": 63, "standardDeviation": 0}, {"startTimeInMillis": 1770015540000, "occurrences": 1, "current": 60, "min": 60, "max": 60, "useRange": false, "count": 1, "sum": 60, "value": 60, "standardDeviation": 0}, {"startTimeInMillis": 1770015600000, "occurrences": 1, "current": 60, "min": 60, "max": 60, "useRange": false, "count": 1, "sum": 60, "value": 60, "standardDeviation": 0}, {"startTimeInMillis": 1770015660000, "occurrences": 1, "current": 66, "min": 66, "max": 66, "useRange": false, "count": 1, "sum": 66, "value": 66, "standardDeviation": 0}, {"startTimeInMillis": 1770015720000, "occurrences": 1, "current": 61, "min": 61, "max": 61, "useRange": false, "count": 1, "sum": 61, "value": 61, "standardDeviation": 0}, {"startTimeInMillis": 1770015780000, "occurrences": 1, "current": 120, "min": 120, "max": 120, "useRange": false, "count": 1, "sum": 120, "value": 120, "standardDeviation": 0}, {"startTimeInMillis": 1770015840000, "occurrences": 1, "current": 123, "min": 123, "max": 123, "useRange": false, "count": 1, "sum": 123, "value": 123, "standardDeviation": 0}, {"startTimeInMillis": 1770015900000, "occurrences": 1, "current": 187, "min": 187, "max": 187, "useRange": false, "count": 1, "sum": 187, "value": 187, "standardDeviation": 0}, {"startTimeInMillis": 1770015960000, "occurrences": 1, "current": 217, "min": 217, "max": 217, "useRange": false, "count": 1, "sum": 217, "value": 217, "standardDeviation": 0}, {"startTimeInMillis": 1770016020000, "occurrences": 1, "current": 186, "min": 186, "max": 186, "useRange": false, "count": 1, "sum": 186, "value": 186, "standardDeviation": 0}, {"startTimeInMillis": 1770016080000, "occurrences": 1, "current": 179, "min": 179, "max": 179, "useRange": false, "count": 1, "sum": 179, "value": 179, "standardDeviation": 0}, {"startTimeInMillis": 1770016140000, "occurrences": 1, "current": 124, "min": 124, "max": 124, "useRange": false, "count": 1, "sum": 124, "value": 124, "standardDeviation": 0}, {"startTimeInMillis": 1770016200000, "occurrences": 1, "current": 120, "min": 120, "max": 120, "useRange": false, "count": 1, "sum": 120, "value": 120, "standardDeviation": 0}, {"startTimeInMillis": 1770016260000, "occurrences": 1, "current": 127, "min": 127, "max": 127, "useRange": false, "count": 1, "sum": 127, "value": 127, "standardDeviation": 0}, {"startTimeInMillis": 1770016320000, "occurrences": 1, "current": 94, "min": 94, "max": 94, "useRange": false, "count": 1, "sum": 94, "value": 94, "standardDeviation": 0}, {"startTimeInMillis": 1770016380000, "occurrences": 1, "current": 61, "min": 61, "max": 61, "useRange": false, "count": 1, "sum": 61, "value": 61, "standardDeviation": 0}, {"startTimeInMillis": 1770016440000, "occurrences": 1, "current": 73, "min": 73, "max": 73, "useRange": false, "count": 1, "sum": 73, "value": 73, "standardDeviation": 0}, {"startTimeInMillis": 1770016500000, "occurrences": 1, "current": 91, "min": 91, "max": 91, "useRange": false, "count": 1, "sum": 91, "value": 91, "standardDeviation": 0}, {"startTimeInMillis": 1770016560000, "occurrences": 1, "current": 78, "min": 78, "max": 78, "useRange": false, "count": 1, "sum": 78, "value": 78, "standardDeviation": 0}, {"startTimeInMillis": 1770016620000, "occurrences": 1, "current": 140, "min": 140, "max": 140, "useRange": false, "count": 1, "sum": 140, "value": 140, "standardDeviation": 0}, {"startTimeInMillis": 1770016680000, "occurrences": 1, "current": 62, "min": 62, "max": 62, "useRange": false, "count": 1, "sum": 62, "value": 62, "standardDeviation": 0}, {"startTimeInMillis": 1770016740000, "occurrences": 1, "current": 85, "min": 85, "max": 85, "useRange": false, "count": 1, "sum": 85, "value": 85, "standardDeviation": 0}, {"startTimeInMillis": 1770016800000, "occurrences": 1, "current": 72, "min": 72, "max": 72, "useRange": false, "count": 1, "sum": 72, "value": 72, "standardDeviation": 0}, {"startTimeInMillis": 1770016860000, "occurrences": 1, "current": 105, "min": 105, "max": 105, "useRange": false, "count": 1, "sum": 105, "value": 105, "standardDeviation": 0}, {"startTimeInMillis": 1770016920000, "occurrences": 1, "current": 120, "min": 120, "max": 120, "useRange": false, "count": 1, "sum": 120, "value": 120, "standardDeviation": 0}, {"startTimeInMillis": 1770016980000, "occurrences": 1, "current": 121, "min": 121, "max": 121, "useRange": false, "count": 1, "sum": 121, "value": 121, "standardDeviation": 0}]}]