[{"metricId": 52796444, "metricName": "BTM|BTs|BT:1286472|Component:478737|Number of Slow Calls", "metricPath": "Business Transaction Performance|Business Transactions|integration-service|/smart-integration/users|Number of Slow Calls", "frequency": "ONE_MIN", "metricValues": [{"startTimeInMillis": 1769504640000, "occurrences": 1, "current": 0, "min": 0, "max": 0, "useRange": false, "count": 0, "sum": 0, "value": 0, "standardDeviation": 0}, {"startTimeInMillis": 1769504700000, "occurrences": 1, "current": 0, "min": 0, "max": 0, "useRange": false, "count": 0, "sum": 0, "value": 0, "standardDeviation": 0}, {"startTimeInMillis": 1769504760000, "occurrences": 1, "current": 0, "min": 0, "max": 0, "useRange": false, "count": 0, "sum": 0, "value": 0, "standardDeviation": 0}, {"startTimeInMillis": 1769504820000, "occurrences": 1, "current": 0, "min": 0, "max": 0, "useRange": false, "count": 0, "sum": 0, "value": 0, "standardDeviation": 0}, {"startTimeInMillis": 1769504880000, "occurrences": 1, "current": 0, "min": 0, "max": 0, "useRange": false, "count": 0, "sum": 0, "value": 0, "standardDeviation": 0}, {"startTimeInMillis": 1769504940000, "occurrences": 1, "current": 0, "min": 0, "max": 0, "useRange": false, "count": 0, "sum": 0, "value": 0, "standardDeviation": 0}, {"startTimeInMillis": 1769505000000, "occurrences": 1, "current": 0, "min": 0, "max": 0, "useRange": false, "count": 0, "sum": 0, "value": 0, "standardDeviation": 0}, {"startTimeInMillis": 1769505060000, "occurrences": 1, "current": 1, "min": 0, "max": 1, "useRange": false, "count": 1, "sum": 1, "value": 1, "standardDeviation": 0}, {"startTimeInMillis": 1769505120000, "occurrences": 1, "current": 0, "min": 0, "max": 0, "useRange": false, "count": 0, "sum": 0, "value": 0, "standardDeviation": 0}, {"startTimeInMillis": 1769505180000, "occurrences": 1, "current": 0, "min": 0, "max": 0, "useRange": false, "count": 0, "sum": 0, "value": 0, "standardDeviation": 0}, {"startTimeInMillis": 1769505240000, "occurrences": 1, "current": 0, "min": 0, "max": 0, "useRange": false, "count": 0, "sum": 0, "value": 0, "standardDeviation": 0}, {"startTimeInMillis": 1769505300000, "occurrences": 1, "current": 0, "min": 0, "max": 0, "useRange": false, "count": 0, "sum": 0, "value": 0, "standardDeviation": 0}, {"startTimeInMillis": 1769505360000, "occurrences": 1, "current": 0, "min": 0, "max": 0, "useRange": false, "count": 0, "sum": 0, "value": 0, "standardDeviation": 0}, {"startTimeInMillis": 1769505420000, "occurrences": 1, "current": 1, "min": 0, "max": 1, "useRange": false, "count": 1, "sum": 1, "value": 1, "standardDeviation": 0}, {"startTimeInMillis": 1769505480000, "occurrences": 1, "current": 0, "min": 0, "max": 0, "useRange": false, "count": 0, "sum": 0, "value": 0, "standardDeviation": 0}, {"startTimeInMillis": 1769505540000, "occurrences": 1, "current": 0, "min": 0, "max": 0, "useRange": false, "count": 0, "sum": 0, "value": 0, "standardDeviation": 0}, {"startTimeInMillis": 1769505600000, "occurrences": 1, "current": 0, "min": 0, "max": 0, "useRange": false, "count": 0, "sum": 0, "value": 0, "standardDeviation": 0}, {"startTimeInMillis": 1769505660000, "occurrences": 1, "current": 0, "min": 0, "max": 0, "useRange": false, "count": 0, "sum": 0, "value": 0, "standardDeviation": 0}, {"startTimeInMillis": 1769505720000, "occurrences": 1, "current": 0, "min": 0, "max": 0, "useRange": false, "count": 0, "sum": 0, "value": 0, "standardDeviation": 0}, {"startTimeInMillis": 1769505780000, "occurrences": 1, "current": 0, "min": 0, "max": 0, "useRange": false, "count": 0, "sum": 0, "value": 0, "standardDeviation": 0}, {"startTimeInMillis": 1769505840000, "occurrences": 1, "current": 0, "min": 0, "max": 0, "useRange": false, "count": 0, "sum": 0, "value": 0, "standardDeviation": 0}, {"startTimeInMillis": 1769505900000, "occurrences": 1, "current": 0, "min": 0, "max": 0, "useRange": false, "count": 1, "sum": 0, "value": 0, "standardDeviation": 0}, {"startTimeInMillis": 1769505960000, "occurrences": 1, "current": 0, "min": 0, "max": 0, "useRange": false, "count": 1, "sum": 0, "value": 0, "standardDeviation": 0}, {"startTimeInMillis": 1769506020000, "occurrences": 1, "current": 0, "min": 0, "max": 0, "useRange": false, "count": 1, "sum": 0, "value": 0, "standardDeviation": 0}, {"startTimeInMillis": 1769506080000, "occurrences": 1, "current": 0, "min": 0, "max": 0, "useRange": false, "count": 1, "sum": 0, "value": 0, "standardDeviation": 0}, {"startTimeInMillis": 1769506140000, "occurrences": 1, "current": 0, "min": 0, "max": 0, "useRange": false, "count": 1, "sum": 0, "value": 0, "standardDeviation": 0}, {"startTimeInMillis": 1769506200000, "occurrences": 1, "current": 0, "min": 0, "max": 0, "useRange": false, "count": 0, "sum": 0, "value": 0, "standardDeviation": 0}, {"startTimeInMillis": 1769506260000, "occurrences": 1, "current": 0, "min": 0, "max": 0, "useRange": false, "count": 0, "sum": 0, "value": 0, "standardDeviation": 0}, {"startTimeInMillis": 1769506320000, "occurrences": 1, "current": 1, "min": 0, "max": 1, "useRange": false, "count": 1, "sum": 1, "value": 1, "standardDeviation": 0}, {"startTimeInMillis": 1769506380000, "occurrences": 1, "current": 0, "min": 0, "max": 0, "useRange": false, "count": 0, "sum": 0, "value": 0, "standardDeviation": 0}, {"startTimeInMillis": 1769506440000, "occurrences": 1, "current": 0, "min": 0, "max": 0, "useRange": false, "count": 0, "sum": 0, "value": 0, "standardDeviation": 0}, {"startTimeInMillis": 1769506500000, "occurrences": 1, "current": 0, "min": 0, "max": 0, "useRange": false, "count": 0, "sum": 0, "value": 0, "standardDeviation": 0}, {"startTimeInMillis": 1769506560000, "occurrences": 1, "current": 0, "min": 0, "max": 0, "useRange": false, "count": 0, "sum": 0, "value": 0, "standardDeviation": 0}, {"startTimeInMillis": 1769506620000, "occurrences": 1, "current": 0, "min": 0, "max": 0, "useRange": false, "count": 0, "sum": 0, "value": 0, "standardDeviation": 0}, {"startTimeInMillis": 1769506680000, "occurrences": 1, "current": 0, "min": 0, "max": 0, "useRange": false, "count": 0, "sum": 0, "value": 0, "standardDeviation": 0}, {"startTimeInMillis": 1769506740000, "occurrences": 1, "current": 0, "min": 0, "max": 0, "useRange": false, "count": 0, "sum": 0, "value": 0, "standardDeviation": 0}, {"startTimeInMillis": 1769506800000, "occurrences": 1, "current": 1, "min": 0, "max": 1, "useRange": false, "count": 1, "sum": 1, "value": 1, "standardDeviation": 0}, {"startTimeInMillis": 1769506860000, "occurrences": 1, "current": 0, "min": 0, "max": 0, "useRange": false, "count": 0, "sum": 0, "value": 0, "standardDeviation": 0}, {"startTimeInMillis": 1769506920000, "occurrences": 1, "current": 0, "min": 0, "max": 0, "useRange": false, "count": 0, "sum": 0, "value": 0, "standardDeviation": 0}, {"startTimeInMillis": 1769506980000, "occurrences": 1, "current": 0, "min": 0, "max": 0, "useRange": false, "count": 0, "sum": 0, "value": 0, "standardDeviation": 0}, {"startTimeInMillis": 1769507040000, "occurrences": 1, "current": 0, "min": 0, "max": 0, "useRange": false, "count": 0, "sum": 0, "value": 0, "standardDeviation": 0}, {"startTimeInMillis": 1769507100000, "occurrences": 1, "current": 0, "min": 0, "max": 0, "useRange": false, "count": 0, "sum": 0, "value": 0, "standardDeviation": 0}, {"startTimeInMillis": 1769507160000, "occurrences": 1, "current": 0, "min": 0, "max": 0, "useRange": false, "count": 0, "sum": 0, "value": 0, "standardDeviation": 0}, {"startTimeInMillis": 1769507220000, "occurrences": 1, "current": 0, "min": 0, "max": 0, "useRange": false, "count": 0, "sum": 0, "value": 0, "standardDeviation": 0}, {"startTimeInMillis": 1769507280000, "occurrences": 1, "current": 0, "min": 0, "max": 0, "useRange": false, "count": 0, "sum": 0, "value": 0, "standardDeviation": 0}, {"startTimeInMillis": 1769507340000, "occurrences": 1, "current": 0, "min": 0, "max": 0, "useRange": false, "count": 0, "sum": 0, "value": 0, "standardDeviation": 0}, {"startTimeInMillis": 1769507400000, "occurrences": 1, "current": 0, "min": 0, "max": 0, "useRange": false, "count": 0, "sum": 0, "value": 0, "standardDeviation": 0}, {"startTimeInMillis": 1769507460000, "occurrences": 1, "current": 0, "min": 0, "max": 0, "useRange": false, "count": 0, "sum": 0, "value": 0, "standardDeviation": 0}, {"startTimeInMillis": 1769507520000, "occurrences": 1, "current": 0, "min": 0, "max": 0, "useRange": false, "count": 0, "sum": 0, "value": 0, "standardDeviation": 0}, {"startTimeInMillis": 1769507580000, "occurrences": 1, "current": 0, "min": 0, "max": 0, "useRange": false, "count": 0, "sum": 0, "value": 0, "standardDeviation": 0}, {"startTimeInMillis": 1769507640000, "occurrences": 1, "current": 0, "min": 0, "max": 0, "useRange": false, "count": 0, "sum": 0, "value": 0, "standardDeviation": 0}, {"startTimeInMillis": 1769507700000, "occurrences": 1, "current": 0, "min": 0, "max": 0, "useRange": false, "count": 0, "sum": 0, "value": 0, "standardDeviation": 0}, {"startTimeInMillis": 1769507760000, "occurrences": 1, "current": 0, "min": 0, "max": 0, "useRange": false, "count": 0, "sum": 0, "value": 0, "standardDeviation": 0}, {"startTimeInMillis": 1769507820000, "occurrences": 1, "current": 0, "min": 0, "max": 0, "useRange": false, "count": 0, "sum": 0, "value": 0, "standardDeviation": 0}, {"startTimeInMillis": 1769507880000, "occurrences": 1, "current": 0, "min": 0, "max": 0, "useRange": false, "count": 0, "sum": 0, "value": 0, "standardDeviation": 0}, {"startTimeInMillis": 1769507940000, "occurrences": 1, "current": 0, "min": 0, "max": 0, "useRange": false, "count": 0, "sum": 0, "value": 0, "standardDeviation": 0}, {"startTimeInMillis": 1769508000000, "occurrences": 1, "current": 0, "min": 0, "max": 0, "useRange": false, "count": 0, "sum": 0, "value": 0, "standardDeviation": 0}, {"startTimeInMillis": 1769508060000, "occurrences": 1, "current": 0, "min": 0, "max": 0, "useRange": false, "count": 0, "sum": 0, "value": 0, "standardDeviation": 0}, {"startTimeInMillis": 1769508120000, "occurrences": 1, "current": 0, "min": 0, "max": 0, "useRange": false, "count": 0, "sum": 0, "value": 0, "standardDeviation": 0}, {"startTimeInMillis": 1769508180000, "occurrences": 1, "current": 0, "min": 0, "max": 0, "useRange": false, "count": 0, "sum": 0, "value": 0, "standardDeviation": 0}]}]